LICENSE
MANIFEST.in
README.md
quicktest.py
settings_test.py
setup.py
django_vkontakte_comments.egg-info/PKG-INFO
django_vkontakte_comments.egg-info/SOURCES.txt
django_vkontakte_comments.egg-info/dependency_links.txt
django_vkontakte_comments.egg-info/not-zip-safe
django_vkontakte_comments.egg-info/requires.txt
django_vkontakte_comments.egg-info/top_level.txt
vkontakte_comments/__init__.py
vkontakte_comments/admin.py
vkontakte_comments/factories.py
vkontakte_comments/mixins.py
vkontakte_comments/models.py
vkontakte_comments/tests.py
vkontakte_comments/migrations/0001_initial.py
vkontakte_comments/migrations/0002_auto__add_field_comment_attachments.py
vkontakte_comments/migrations/__init__.py