Metadata-Version: 1.1
Name: django-vkontakte-comments
Version: 0.8.2
Summary: Django implementation for vkontakte API comments
Home-page: https://github.com/Andertaker/django-vkontakte-comments
Author: krupin.dv
Author-email: krupin.dv19@gmail.com
License: BSD
Download-URL: http://pypi.python.org/pypi/django-vkontakte-comments
Platform: UNKNOWN
Classifier: Development Status :: 4 - Beta
Classifier: Environment :: Web Environment
Classifier: Intended Audience :: Developers
Classifier: License :: OSI Approved :: BSD License
Classifier: Operating System :: OS Independent
Classifier: Programming Language :: Python
Classifier: Topic :: Software Development :: Libraries :: Python Modules
